Metadata-Version: 2.1
Name: odoo-addon-account_financial_report_operating_unit
Version: 17.0.1.0.0.9
Requires-Python: >=3.10
Requires-Dist: odoo-addon-account_financial_report>=17.0dev,<17.1dev
Requires-Dist: odoo-addon-account_operating_unit>=17.0dev,<17.1dev
Requires-Dist: odoo>=17.0a,<17.1dev
Summary: Introduces Operating Unit (OU) in financial reports
Home-page: https://github.com/OCA/operating-unit
License: AGPL-3
Author: Ecosoft, Odoo Community Association (OCA)
Author-email: support@odoo-community.org
Classifier: Programming Language :: Python
Classifier: Framework :: Odoo
Classifier: Framework :: Odoo :: 17.0
Classifier: License :: OSI Approved :: GNU Affero General Public License v3
